coap_console/__init__.py
coap_console-0.0.3.dist-info/METADATA
coap_console-0.0.3.dist-info/WHEEL
coap_console-0.0.3.dist-info/entry_points.txt
coap_console-0.0.3.dist-info/top_level.txt
coap_console-0.0.3.dist-info/RECORD
