Metadata-Version: 2.1
Name: coap_console
Version: 0.0.3
Summary: CoAP client for interactive with remote serial input and output
Author-email: chrysn <chrysn@fsfe.org>
License: MIT OR Apache-2.0
Project-URL: Homepage, https://gitlab.com/chrysn/scroll-ring
Project-URL: Issues, https://gitlab.com/chrysn/scroll-ring/-/issues
Classifier: Programming Language :: Python :: 3
Classifier: License :: OSI Approved :: MIT License
Classifier: License :: OSI Approved :: Apache Software License
Classifier: Operating System :: OS Independent
Requires-Python: >=3.10
Requires-Dist: aiocoap[oscore]<0.5,>=0.4.12
Requires-Dist: cbor2
Requires-Dist: cbor-diag
